gobnb/__init__.py
gobnb/api.py
gobnb/details.py
gobnb/parse.py
gobnb/price.py
gobnb/search.py
gobnb/standardize.py
gobnb/utils.py
gobnb-0.0.12.dist-info/LICENSE
gobnb-0.0.12.dist-info/METADATA
gobnb-0.0.12.dist-info/WHEEL
gobnb-0.0.12.dist-info/top_level.txt
gobnb-0.0.12.dist-info/RECORD
