Metadata-Version: 2.1
Name: gobnb
Version: 0.0.12
Summary: Airbnb scraper in Python
Home-page: https://github.com/johnbalvin/pyairbnbb
Author: John (John Balvin)
Author-email: John Balvin <johnchristian@hotmail.es>
Project-URL: Homepage, https://github.com/johnbalvin/pyairbnb
Keywords: airbnb,scraper,crawler,requests
License-File: LICENSE
Requires-Dist: curl-cffi
Requires-Dist: bs4
Requires-Dist: requests
